btcpay_django/__init__.py
btcpay_django/admin.py
btcpay_django/app_settings.py
btcpay_django/migrations/0001_initial.py
btcpay_django/migrations/__init__.py
btcpay_django/models.py
btcpay_django/utils.py
btcpay_django-0.0.1.dist-info/LICENSE
btcpay_django-0.0.1.dist-info/WHEEL
btcpay_django-0.0.1.dist-info/METADATA
btcpay_django-0.0.1.dist-info/RECORD
