Metadata-Version: 2.1
Name: btcpay-django
Version: 0.0.1
Summary: 
License: MIT
Author: Crawford Leeds
Author-email: crawford@crawfordleeds.com
Requires-Python: >=3.6,<4.0
Classifier: Development Status :: 2 - Pre-Alpha
Classifier: Intended Audience :: Developers
Classifier: License :: OSI Approved :: MIT License
Classifier: Natural Language :: English
Classifier: Programming Language :: Python :: 3
Classifier: Programming Language :: Python :: 3.6
Classifier: Programming Language :: Python :: 3.7
Classifier: Programming Language :: Python :: 3.8
Classifier: Programming Language :: Python :: 3.9
Requires-Dist: Django (>=2.2)
Requires-Dist: btcpay-python (>=1.3.0,<2.0.0)
Requires-Dist: django-crawfish (>=0.0.8,<0.0.9)
